dmn_python/DMNExport.py
dmn_python/DMNImport.py
dmn_python/DMNVisualisation.py
dmn_python-0.1.4.1.dist-info/DESCRIPTION.rst
dmn_python-0.1.4.1.dist-info/METADATA
dmn_python-0.1.4.1.dist-info/RECORD
dmn_python-0.1.4.1.dist-info/WHEEL
dmn_python-0.1.4.1.dist-info/metadata.json
dmn_python-0.1.4.1.dist-info/top_level.txt
